main.py
server.py
tools/__init__.py
tools/get_resolution_issue.py
utils/__init__.py
utils/llm_call.py
jira_mcp-0.1.4.dist-info/METADATA
jira_mcp-0.1.4.dist-info/WHEEL
jira_mcp-0.1.4.dist-info/entry_points.txt
jira_mcp-0.1.4.dist-info/top_level.txt
jira_mcp-0.1.4.dist-info/RECORD
